setup.py
Distributions_Pack_Testing/Binomialdistribution.py
Distributions_Pack_Testing/Gaussiandistribution.py
Distributions_Pack_Testing/Generaldistribution.py
Distributions_Pack_Testing/__init__.py
Distributions_Pack_Testing.egg-info/PKG-INFO
Distributions_Pack_Testing.egg-info/SOURCES.txt
Distributions_Pack_Testing.egg-info/dependency_links.txt
Distributions_Pack_Testing.egg-info/not-zip-safe
Distributions_Pack_Testing.egg-info/top_level.txt