Metadata-Version: 1.0
Name: Distributions-Pack-Testing
Version: 1.0
Summary: Gaussian Distributions_Pack_Testing
Home-page: UNKNOWN
Author: Harish Mohanaselvam
Author-email: harish.msl@hotmail.com
License: UNKNOWN
Platform: UNKNOWN
